hassa/__init__.py
hassa/hassa.py
hassa-0.1.0.dist-info/LICENSE.txt
hassa-0.1.0.dist-info/METADATA
hassa-0.1.0.dist-info/WHEEL
hassa-0.1.0.dist-info/top_level.txt
hassa-0.1.0.dist-info/RECORD
