Metadata-Version: 2.1
Name: hassa
Version: 0.1.0
Summary: A short description of my package
Author: hassan
Author-email: husseun.selt@gmail.com
Classifier: Programming Language :: Python :: 3
Classifier: License :: OSI Approved :: MIT License
Classifier: Operating System :: OS Independent
Requires-Python: >=3.6
License-File: LICENSE.txt
